ViperEngine/Viper.py
ViperEngine/__init__.py
ViperEngine/constants.py
viperengine-1.1.3.dist-info/METADATA
viperengine-1.1.3.dist-info/WHEEL
viperengine-1.1.3.dist-info/entry_points.txt
viperengine-1.1.3.dist-info/top_level.txt
viperengine-1.1.3.dist-info/RECORD
