Metadata-Version: 2.1
Name: ViperEngine
Version: 1.1.3
Summary: Minimal pygame-like 2D game framework using SDL2 and ctypes
Author: Aynu
Classifier: Programming Language :: Python :: 3
Classifier: License :: OSI Approved :: MIT License
Classifier: Operating System :: OS Independent
Classifier: Topic :: Games/Entertainment
Classifier: Intended Audience :: Developers
Classifier: Development Status :: 3 - Alpha
Requires-Python: >=3.6
